<annotation>
	<folder>extended</folder>
	<filename>Screenshot 2019-10-08 13.18.24.png</filename>
	<path>W:\02CURE formula student\CURENet\Datset_tracking\data\images\extended\Screenshot 2019-10-08 13.18.24.png</path>
	<source>
		<database>Unknown</database>
	</source>
	<size>
		<width>1274</width>
		<height>718</height>
		<depth>3</depth>
	</size>
	<segmented>0</segmented>
	<object>
		<name>lcone</name>
		<pose>Unspecified</pose>
		<truncated>0</truncated>
		<difficult>0</difficult>
		<bndbox>
			<xmin>293</xmin>
			<ymin>343</ymin>
			<xmax>362</xmax>
			<ymax>434</ymax>
		</bndbox>
	</object>
	<object>
		<name>lcone</name>
		<pose>Unspecified</pose>
		<truncated>0</truncated>
		<difficult>0</difficult>
		<bndbox>
			<xmin>612</xmin>
			<ymin>230</ymin>
			<xmax>643</xmax>
			<ymax>270</ymax>
		</bndbox>
	</object>
	<object>
		<name>lcone</name>
		<pose>Unspecified</pose>
		<truncated>0</truncated>
		<difficult>0</difficult>
		<bndbox>
			<xmin>832</xmin>
			<ymin>208</ymin>
			<xmax>856</xmax>
			<ymax>238</ymax>
		</bndbox>
	</object>
	<object>
		<name>rcone</name>
		<pose>Unspecified</pose>
		<truncated>0</truncated>
		<difficult>0</difficult>
		<bndbox>
			<xmin>1169</xmin>
			<ymin>404</ymin>
			<xmax>1251</xmax>
			<ymax>501</ymax>
		</bndbox>
	</object>
	<object>
		<name>rcone</name>
		<pose>Unspecified</pose>
		<truncated>0</truncated>
		<difficult>0</difficult>
		<bndbox>
			<xmin>1068</xmin>
			<ymin>270</ymin>
			<xmax>1105</xmax>
			<ymax>319</ymax>
		</bndbox>
	</object>
	<object>
		<name>rcone</name>
		<pose>Unspecified</pose>
		<truncated>0</truncated>
		<difficult>0</difficult>
		<bndbox>
			<xmin>1198</xmin>
			<ymin>264</ymin>
			<xmax>1228</xmax>
			<ymax>302</ymax>
		</bndbox>
	</object>
</annotation>
